unfazed_sentry/__init__.py
unfazed_sentry/base.py
unfazed_sentry/lifespan.py
unfazed_sentry/settings.py
unfazed_sentry/middleware/common.py
unfazed_sentry-0.0.2.dist-info/METADATA
unfazed_sentry-0.0.2.dist-info/WHEEL
unfazed_sentry-0.0.2.dist-info/licenses/LICENSE
unfazed_sentry-0.0.2.dist-info/RECORD
