Metadata-Version: 2.4
Name: unfazed-sentry
Version: 0.0.2
Summary: Sentry client for Unfazed
License-File: LICENSE
Requires-Dist: sentry-sdk>=2.22.0
Requires-Dist: unfazed>=0.0.7
